imzml_writer/Images/Logo-01.png
imzml_writer/Images/imzML_Writer.ico
imzml_writer/__init__.py
imzml_writer/analyte_list_cleanup.py
imzml_writer/cmap_targets.json
imzml_writer/imzML_Scout.py
imzml_writer/imzML_Writer.py
imzml_writer/ms_convert_gui.py
imzml_writer/recalibrate_mz.py
imzml_writer/scout_utils.py
imzml_writer/utils.py
imzml_writer-1.2.2.dist-info/METADATA
imzml_writer-1.2.2.dist-info/WHEEL
imzml_writer-1.2.2.dist-info/RECORD
