Metadata-Version: 2.3
Name: imzML-Writer
Version: 1.2.2
Summary: "User friendly writing of imzML mass spectrometry imaging files from continuous MSI data"
License: MIT
Author: Joseph Monaghan
Author-email: Joseph_Monaghan@outlook.com
Requires-Python: >=3.10
Classifier: License :: OSI Approved :: MIT License
Classifier: Programming Language :: Python :: 3
Classifier: Programming Language :: Python :: 3.10
Classifier: Programming Language :: Python :: 3.11
Classifier: Programming Language :: Python :: 3.12
Classifier: Programming Language :: Python :: 3.13
Requires-Dist: beautifulsoup4 (>=4.13.3,<5.0.0)
Requires-Dist: docker (>=7.1.0,<8.0.0)
Requires-Dist: lxml (>=5.3.1,<6.0.0)
Requires-Dist: matplotlib (>=3.10.0,<4.0.0)
Requires-Dist: numpy (>=2.2.3,<3.0.0)
Requires-Dist: opencv-python (>=4.11.0.86,<5.0.0.0)
Requires-Dist: openpyxl (>=3.1.5,<4.0.0)
Requires-Dist: pandas (>=2.2.3,<3.0.0)
Requires-Dist: pyimzml (>=1.5.5,<2.0.0)
Requires-Dist: pymzml (>=2.5.11,<3.0.0)
Requires-Dist: rangeslider (>=2023.7.2,<2024.0.0)
Requires-Dist: scipy (>=1.15.2,<2.0.0)
